Metadata-Version: 2.1
Name: rokcetshipy
Version: 1.0.0
Summary: An awesome package that does something
Home-page: http://pypi.python.org/pypi/rokcetshipy/
Author: Abdelmoumen Deghbouche
Author-email: a.deghbouche@esi-sba.dz
License: LICENSE.txt
License-File: LICENSE.txt
Requires-Dist: rokcetshipy
